git_template_repo/__init__.py
git_template_repo/__main__.py
git_template_repo/_version.py
git_template_repo/git_template_repo.py
git_template_repo-1.0.1.dist-info/METADATA
git_template_repo-1.0.1.dist-info/WHEEL
git_template_repo-1.0.1.dist-info/entry_points.txt
git_template_repo-1.0.1.dist-info/licenses/LICENSE
git_template_repo-1.0.1.dist-info/RECORD
