Metadata-Version: 2.1
Name: git-template-repo
Version: 1.0.1
Summary: A git command for creating a git repository from another repository as a template.
Project-URL: Homepage, https://github.com/IDI-Systems/git-template-repo
Project-URL: Bug Tracker, https://github.com/IDI-Systems/git-template-repo
Author-email: IDI-Systems <contact@idi-systems.com>
License-Expression: MIT
License-File: LICENSE
Classifier: Development Status :: 4 - Beta
Classifier: Environment :: Console
Classifier: Intended Audience :: Developers
Classifier: License :: OSI Approved :: MIT License
Classifier: Operating System :: OS Independent
Classifier: Programming Language :: Python :: 3.7
Classifier: Programming Language :: Python :: 3.8
Classifier: Programming Language :: Python :: 3.9
Classifier: Programming Language :: Python :: 3.10
Classifier: Programming Language :: Python :: 3.11
Classifier: Topic :: Software Development :: Version Control :: Git
Requires-Python: >=3.7
